{
  "generated_at": "2026-02-15T04:01:23.241963Z",
  "strategy": {
    "name": "overreaction_reversion",
    "mode": "paper_only",
    "assets": [
      "BTC",
      "ETH",
      "SOL"
    ],
    "available": [
      "overreaction_reversion",
      "sports_odds_dislocation",
      "spot_edge"
    ],
    "series_tickers": [
      "KXBTC15M",
      "KXETH15M",
      "KXSOL15M"
    ],
    "poll_seconds": 10,
    "parallel": true,
    "rules": {
      "trade_assets": [
        "BTC",
        "ETH",
        "SOL"
      ],
      "allow_no_trades": false,
      "take_profit_cents": 8,
      "stop_loss_cents": 4,
      "max_hold_minutes": 0,
      "min_volume": 10,
      "max_spread_cents": 6,
      "spike_filter_bps": 35.0,
      "max_open_positions": 3,
      "min_momentum_bps": 3.0,
      "min_edge_cents": 3.0,
      "reversion_z_threshold": 1.7,
      "reversion_min_edge_cents": 1.2,
      "min_dislocation_cents": null
    },
    "configs": {
      "overreaction_reversion": {
        "trade_assets": [
          "BTC",
          "ETH",
          "SOL"
        ],
        "allow_no_trades": false,
        "take_profit_cents": 8,
        "stop_loss_cents": 4,
        "max_hold_minutes": 0,
        "min_volume": 10,
        "max_spread_cents": 6,
        "spike_filter_bps": 35.0,
        "max_open_positions": 3,
        "min_momentum_bps": 3.0,
        "min_edge_cents": 3.0,
        "reversion_z_threshold": 1.7,
        "reversion_min_edge_cents": 1.2,
        "min_dislocation_cents": null
      },
      "sports_odds_dislocation": {
        "trade_assets": [
          "SPORTS"
        ],
        "allow_no_trades": false,
        "take_profit_cents": 10,
        "stop_loss_cents": 6,
        "max_hold_minutes": 0,
        "min_volume": 0,
        "max_spread_cents": 12,
        "spike_filter_bps": 37,
        "max_open_positions": 5,
        "min_momentum_bps": 2.5,
        "min_edge_cents": 2.5,
        "reversion_z_threshold": 1.8,
        "reversion_min_edge_cents": 1.5,
        "min_dislocation_cents": 0.1
      },
      "spot_edge": {
        "trade_assets": [
          "BTC",
          "ETH",
          "SOL"
        ],
        "allow_no_trades": true,
        "take_profit_cents": 8,
        "stop_loss_cents": 4,
        "max_hold_minutes": 0,
        "min_volume": 10,
        "max_spread_cents": 6,
        "spike_filter_bps": 36.0,
        "max_open_positions": 3,
        "min_momentum_bps": 2.5,
        "min_edge_cents": 3.0,
        "reversion_z_threshold": 1.8,
        "reversion_min_edge_cents": 1.5,
        "min_dislocation_cents": null
      }
    }
  },
  "loop": {
    "active": true,
    "last_updated": "2026-02-15T04:01:22.972970Z",
    "focused_market_count_last_cycle": 6,
    "recent_cycles": [
      {
        "time": "2026-02-15T03:59:34.751492Z",
        "strategy": "spot_edge",
        "focused_market_count": 3,
        "open_positions": 2,
        "opened": [],
        "closed": [],
        "realized_pnl_cents": -1745.0,
        "unrealized_pnl_cents": 10.0,
        "total_pnl_cents": -1735.0
      },
      {
        "time": "2026-02-15T03:59:47.503950Z",
        "strategy": "overreaction_reversion",
        "focused_market_count": 3,
        "open_positions": 1,
        "opened": [],
        "closed": [],
        "realized_pnl_cents": -1625.0,
        "unrealized_pnl_cents": -3.0,
        "total_pnl_cents": -1628.0
      },
      {
        "time": "2026-02-15T03:59:48.550910Z",
        "strategy": "sports_odds_dislocation",
        "focused_market_count": 0,
        "open_positions": 0,
        "opened": [],
        "closed": [],
        "realized_pnl_cents": -3329.97,
        "unrealized_pnl_cents": 0,
        "total_pnl_cents": -3329.97
      },
      {
        "time": "2026-02-15T03:59:49.941190Z",
        "strategy": "spot_edge",
        "focused_market_count": 3,
        "open_positions": 2,
        "opened": [],
        "closed": [],
        "realized_pnl_cents": -1745.0,
        "unrealized_pnl_cents": 10.0,
        "total_pnl_cents": -1735.0
      },
      {
        "time": "2026-02-15T04:00:02.669683Z",
        "strategy": "overreaction_reversion",
        "focused_market_count": 3,
        "open_positions": 1,
        "opened": [],
        "closed": [],
        "realized_pnl_cents": -1625.0,
        "unrealized_pnl_cents": -3.0,
        "total_pnl_cents": -1628.0
      },
      {
        "time": "2026-02-15T04:00:03.743647Z",
        "strategy": "sports_odds_dislocation",
        "focused_market_count": 0,
        "open_positions": 0,
        "opened": [],
        "closed": [],
        "realized_pnl_cents": -3329.97,
        "unrealized_pnl_cents": 0,
        "total_pnl_cents": -3329.97
      },
      {
        "time": "2026-02-15T04:00:05.215836Z",
        "strategy": "spot_edge",
        "focused_market_count": 3,
        "open_positions": 2,
        "opened": [],
        "closed": [],
        "realized_pnl_cents": -1745.0,
        "unrealized_pnl_cents": 10.0,
        "total_pnl_cents": -1735.0
      },
      {
        "time": "2026-02-15T04:00:18.027757Z",
        "strategy": "overreaction_reversion",
        "focused_market_count": 3,
        "open_positions": 1,
        "opened": [],
        "closed": [],
        "realized_pnl_cents": -1625.0,
        "unrealized_pnl_cents": -3.0,
        "total_pnl_cents": -1628.0
      },
      {
        "time": "2026-02-15T04:00:18.975933Z",
        "strategy": "sports_odds_dislocation",
        "focused_market_count": 0,
        "open_positions": 0,
        "opened": [],
        "closed": [],
        "realized_pnl_cents": -3329.97,
        "unrealized_pnl_cents": 0,
        "total_pnl_cents": -3329.97
      },
      {
        "time": "2026-02-15T04:00:20.458208Z",
        "strategy": "spot_edge",
        "focused_market_count": 3,
        "open_positions": 3,
        "opened": [
          {
            "ticker": "KXBTC15M-26FEB142315-15",
            "asset": "BTC",
            "side": "YES",
            "entry": 55.0,
            "score": 22.9,
            "strategy": "spot_edge"
          }
        ],
        "closed": [],
        "realized_pnl_cents": -1745.0,
        "unrealized_pnl_cents": 10.0,
        "total_pnl_cents": -1735.0
      },
      {
        "time": "2026-02-15T04:00:33.972522Z",
        "strategy": "sports_odds_dislocation",
        "focused_market_count": 0,
        "open_positions": 0,
        "opened": [],
        "closed": [],
        "realized_pnl_cents": -3329.97,
        "unrealized_pnl_cents": 0,
        "total_pnl_cents": -3329.97
      },
      {
        "time": "2026-02-15T04:00:47.978403Z",
        "strategy": "overreaction_reversion",
        "focused_market_count": 3,
        "open_positions": 1,
        "opened": [],
        "closed": [],
        "realized_pnl_cents": -1625.0,
        "unrealized_pnl_cents": -3.0,
        "total_pnl_cents": -1628.0
      },
      {
        "time": "2026-02-15T04:00:48.912237Z",
        "strategy": "sports_odds_dislocation",
        "focused_market_count": 0,
        "open_positions": 0,
        "opened": [],
        "closed": [],
        "realized_pnl_cents": -3329.97,
        "unrealized_pnl_cents": 0,
        "total_pnl_cents": -3329.97
      },
      {
        "time": "2026-02-15T04:00:50.320280Z",
        "strategy": "spot_edge",
        "focused_market_count": 3,
        "open_positions": 3,
        "opened": [],
        "closed": [],
        "realized_pnl_cents": -1745.0,
        "unrealized_pnl_cents": 9.0,
        "total_pnl_cents": -1736.0
      },
      {
        "time": "2026-02-15T04:01:03.122656Z",
        "strategy": "overreaction_reversion",
        "focused_market_count": 3,
        "open_positions": 1,
        "opened": [],
        "closed": [],
        "realized_pnl_cents": -1625.0,
        "unrealized_pnl_cents": -3.0,
        "total_pnl_cents": -1628.0
      },
      {
        "time": "2026-02-15T04:01:03.997050Z",
        "strategy": "sports_odds_dislocation",
        "focused_market_count": 0,
        "open_positions": 0,
        "opened": [],
        "closed": [],
        "realized_pnl_cents": -3329.97,
        "unrealized_pnl_cents": 0,
        "total_pnl_cents": -3329.97
      },
      {
        "time": "2026-02-15T04:01:05.530459Z",
        "strategy": "spot_edge",
        "focused_market_count": 3,
        "open_positions": 3,
        "opened": [],
        "closed": [],
        "realized_pnl_cents": -1745.0,
        "unrealized_pnl_cents": 8.0,
        "total_pnl_cents": -1737.0
      },
      {
        "time": "2026-02-15T04:01:18.742129Z",
        "strategy": "overreaction_reversion",
        "focused_market_count": 3,
        "open_positions": 1,
        "opened": [],
        "closed": [],
        "realized_pnl_cents": -1625.0,
        "unrealized_pnl_cents": -3.0,
        "total_pnl_cents": -1628.0
      },
      {
        "time": "2026-02-15T04:01:19.695591Z",
        "strategy": "sports_odds_dislocation",
        "focused_market_count": 0,
        "open_positions": 0,
        "opened": [],
        "closed": [],
        "realized_pnl_cents": -3329.97,
        "unrealized_pnl_cents": 0,
        "total_pnl_cents": -3329.97
      },
      {
        "time": "2026-02-15T04:01:22.995605Z",
        "strategy": "spot_edge",
        "focused_market_count": 3,
        "open_positions": 3,
        "opened": [],
        "closed": [],
        "realized_pnl_cents": -1745.0,
        "unrealized_pnl_cents": 7.0,
        "total_pnl_cents": -1738.0
      }
    ],
    "by_strategy": {
      "overreaction_reversion": {
        "active": true,
        "last_updated": "2026-02-15T04:01:18.730884Z",
        "focused_market_count_last_cycle": 3,
        "recent_cycles": [
          {
            "time": "2026-02-15T03:58:17.265292Z",
            "strategy": "overreaction_reversion",
            "focused_market_count": 3,
            "open_positions": 1,
            "opened": [],
            "closed": [],
            "realized_pnl_cents": -1625.0,
            "unrealized_pnl_cents": -3.0,
            "total_pnl_cents": -1628.0
          },
          {
            "time": "2026-02-15T03:58:32.356973Z",
            "strategy": "overreaction_reversion",
            "focused_market_count": 3,
            "open_positions": 1,
            "opened": [],
            "closed": [],
            "realized_pnl_cents": -1625.0,
            "unrealized_pnl_cents": -3.0,
            "total_pnl_cents": -1628.0
          },
          {
            "time": "2026-02-15T03:58:47.657487Z",
            "strategy": "overreaction_reversion",
            "focused_market_count": 3,
            "open_positions": 1,
            "opened": [],
            "closed": [],
            "realized_pnl_cents": -1625.0,
            "unrealized_pnl_cents": -3.0,
            "total_pnl_cents": -1628.0
          },
          {
            "time": "2026-02-15T03:59:02.768543Z",
            "strategy": "overreaction_reversion",
            "focused_market_count": 3,
            "open_positions": 1,
            "opened": [],
            "closed": [],
            "realized_pnl_cents": -1625.0,
            "unrealized_pnl_cents": -3.0,
            "total_pnl_cents": -1628.0
          },
          {
            "time": "2026-02-15T03:59:17.594886Z",
            "strategy": "overreaction_reversion",
            "focused_market_count": 3,
            "open_positions": 1,
            "opened": [],
            "closed": [],
            "realized_pnl_cents": -1625.0,
            "unrealized_pnl_cents": -3.0,
            "total_pnl_cents": -1628.0
          },
          {
            "time": "2026-02-15T03:59:32.418770Z",
            "strategy": "overreaction_reversion",
            "focused_market_count": 3,
            "open_positions": 1,
            "opened": [],
            "closed": [],
            "realized_pnl_cents": -1625.0,
            "unrealized_pnl_cents": -3.0,
            "total_pnl_cents": -1628.0
          },
          {
            "time": "2026-02-15T03:59:47.503950Z",
            "strategy": "overreaction_reversion",
            "focused_market_count": 3,
            "open_positions": 1,
            "opened": [],
            "closed": [],
            "realized_pnl_cents": -1625.0,
            "unrealized_pnl_cents": -3.0,
            "total_pnl_cents": -1628.0
          },
          {
            "time": "2026-02-15T04:00:02.669683Z",
            "strategy": "overreaction_reversion",
            "focused_market_count": 3,
            "open_positions": 1,
            "opened": [],
            "closed": [],
            "realized_pnl_cents": -1625.0,
            "unrealized_pnl_cents": -3.0,
            "total_pnl_cents": -1628.0
          },
          {
            "time": "2026-02-15T04:00:18.027757Z",
            "strategy": "overreaction_reversion",
            "focused_market_count": 3,
            "open_positions": 1,
            "opened": [],
            "closed": [],
            "realized_pnl_cents": -1625.0,
            "unrealized_pnl_cents": -3.0,
            "total_pnl_cents": -1628.0
          },
          {
            "time": "2026-02-15T04:00:47.978403Z",
            "strategy": "overreaction_reversion",
            "focused_market_count": 3,
            "open_positions": 1,
            "opened": [],
            "closed": [],
            "realized_pnl_cents": -1625.0,
            "unrealized_pnl_cents": -3.0,
            "total_pnl_cents": -1628.0
          },
          {
            "time": "2026-02-15T04:01:03.122656Z",
            "strategy": "overreaction_reversion",
            "focused_market_count": 3,
            "open_positions": 1,
            "opened": [],
            "closed": [],
            "realized_pnl_cents": -1625.0,
            "unrealized_pnl_cents": -3.0,
            "total_pnl_cents": -1628.0
          },
          {
            "time": "2026-02-15T04:01:18.742129Z",
            "strategy": "overreaction_reversion",
            "focused_market_count": 3,
            "open_positions": 1,
            "opened": [],
            "closed": [],
            "realized_pnl_cents": -1625.0,
            "unrealized_pnl_cents": -3.0,
            "total_pnl_cents": -1628.0
          }
        ],
        "open_positions": 1,
        "total_pnl_cents": -1628.0
      },
      "sports_odds_dislocation": {
        "active": true,
        "last_updated": "2026-02-15T04:01:19.694530Z",
        "focused_market_count_last_cycle": 0,
        "recent_cycles": [
          {
            "time": "2026-02-15T03:58:33.308471Z",
            "strategy": "sports_odds_dislocation",
            "focused_market_count": 0,
            "open_positions": 0,
            "opened": [],
            "closed": [],
            "realized_pnl_cents": -3329.97,
            "unrealized_pnl_cents": 0,
            "total_pnl_cents": -3329.97
          },
          {
            "time": "2026-02-15T03:58:48.737028Z",
            "strategy": "sports_odds_dislocation",
            "focused_market_count": 0,
            "open_positions": 0,
            "opened": [],
            "closed": [],
            "realized_pnl_cents": -3329.97,
            "unrealized_pnl_cents": 0,
            "total_pnl_cents": -3329.97
          },
          {
            "time": "2026-02-15T03:59:03.682315Z",
            "strategy": "sports_odds_dislocation",
            "focused_market_count": 0,
            "open_positions": 0,
            "opened": [],
            "closed": [],
            "realized_pnl_cents": -3329.97,
            "unrealized_pnl_cents": 0,
            "total_pnl_cents": -3329.97
          },
          {
            "time": "2026-02-15T03:59:18.507833Z",
            "strategy": "sports_odds_dislocation",
            "focused_market_count": 0,
            "open_positions": 0,
            "opened": [],
            "closed": [],
            "realized_pnl_cents": -3329.97,
            "unrealized_pnl_cents": 0,
            "total_pnl_cents": -3329.97
          },
          {
            "time": "2026-02-15T03:59:33.362989Z",
            "strategy": "sports_odds_dislocation",
            "focused_market_count": 0,
            "open_positions": 0,
            "opened": [],
            "closed": [],
            "realized_pnl_cents": -3329.97,
            "unrealized_pnl_cents": 0,
            "total_pnl_cents": -3329.97
          },
          {
            "time": "2026-02-15T03:59:48.550910Z",
            "strategy": "sports_odds_dislocation",
            "focused_market_count": 0,
            "open_positions": 0,
            "opened": [],
            "closed": [],
            "realized_pnl_cents": -3329.97,
            "unrealized_pnl_cents": 0,
            "total_pnl_cents": -3329.97
          },
          {
            "time": "2026-02-15T04:00:03.743647Z",
            "strategy": "sports_odds_dislocation",
            "focused_market_count": 0,
            "open_positions": 0,
            "opened": [],
            "closed": [],
            "realized_pnl_cents": -3329.97,
            "unrealized_pnl_cents": 0,
            "total_pnl_cents": -3329.97
          },
          {
            "time": "2026-02-15T04:00:18.975933Z",
            "strategy": "sports_odds_dislocation",
            "focused_market_count": 0,
            "open_positions": 0,
            "opened": [],
            "closed": [],
            "realized_pnl_cents": -3329.97,
            "unrealized_pnl_cents": 0,
            "total_pnl_cents": -3329.97
          },
          {
            "time": "2026-02-15T04:00:33.972522Z",
            "strategy": "sports_odds_dislocation",
            "focused_market_count": 0,
            "open_positions": 0,
            "opened": [],
            "closed": [],
            "realized_pnl_cents": -3329.97,
            "unrealized_pnl_cents": 0,
            "total_pnl_cents": -3329.97
          },
          {
            "time": "2026-02-15T04:00:48.912237Z",
            "strategy": "sports_odds_dislocation",
            "focused_market_count": 0,
            "open_positions": 0,
            "opened": [],
            "closed": [],
            "realized_pnl_cents": -3329.97,
            "unrealized_pnl_cents": 0,
            "total_pnl_cents": -3329.97
          },
          {
            "time": "2026-02-15T04:01:03.997050Z",
            "strategy": "sports_odds_dislocation",
            "focused_market_count": 0,
            "open_positions": 0,
            "opened": [],
            "closed": [],
            "realized_pnl_cents": -3329.97,
            "unrealized_pnl_cents": 0,
            "total_pnl_cents": -3329.97
          },
          {
            "time": "2026-02-15T04:01:19.695591Z",
            "strategy": "sports_odds_dislocation",
            "focused_market_count": 0,
            "open_positions": 0,
            "opened": [],
            "closed": [],
            "realized_pnl_cents": -3329.97,
            "unrealized_pnl_cents": 0,
            "total_pnl_cents": -3329.97
          }
        ],
        "open_positions": 0,
        "total_pnl_cents": -3329.97
      },
      "spot_edge": {
        "active": true,
        "last_updated": "2026-02-15T04:01:22.972970Z",
        "focused_market_count_last_cycle": 3,
        "recent_cycles": [
          {
            "time": "2026-02-15T03:58:19.620311Z",
            "strategy": "spot_edge",
            "focused_market_count": 3,
            "open_positions": 2,
            "opened": [],
            "closed": [],
            "realized_pnl_cents": -1745.0,
            "unrealized_pnl_cents": 10.0,
            "total_pnl_cents": -1735.0
          },
          {
            "time": "2026-02-15T03:58:34.830978Z",
            "strategy": "spot_edge",
            "focused_market_count": 3,
            "open_positions": 2,
            "opened": [],
            "closed": [],
            "realized_pnl_cents": -1745.0,
            "unrealized_pnl_cents": 10.0,
            "total_pnl_cents": -1735.0
          },
          {
            "time": "2026-02-15T03:58:50.178488Z",
            "strategy": "spot_edge",
            "focused_market_count": 3,
            "open_positions": 2,
            "opened": [],
            "closed": [],
            "realized_pnl_cents": -1745.0,
            "unrealized_pnl_cents": 10.0,
            "total_pnl_cents": -1735.0
          },
          {
            "time": "2026-02-15T03:59:05.087568Z",
            "strategy": "spot_edge",
            "focused_market_count": 3,
            "open_positions": 2,
            "opened": [],
            "closed": [],
            "realized_pnl_cents": -1745.0,
            "unrealized_pnl_cents": 10.0,
            "total_pnl_cents": -1735.0
          },
          {
            "time": "2026-02-15T03:59:19.823361Z",
            "strategy": "spot_edge",
            "focused_market_count": 3,
            "open_positions": 2,
            "opened": [],
            "closed": [],
            "realized_pnl_cents": -1745.0,
            "unrealized_pnl_cents": 10.0,
            "total_pnl_cents": -1735.0
          },
          {
            "time": "2026-02-15T03:59:34.751492Z",
            "strategy": "spot_edge",
            "focused_market_count": 3,
            "open_positions": 2,
            "opened": [],
            "closed": [],
            "realized_pnl_cents": -1745.0,
            "unrealized_pnl_cents": 10.0,
            "total_pnl_cents": -1735.0
          },
          {
            "time": "2026-02-15T03:59:49.941190Z",
            "strategy": "spot_edge",
            "focused_market_count": 3,
            "open_positions": 2,
            "opened": [],
            "closed": [],
            "realized_pnl_cents": -1745.0,
            "unrealized_pnl_cents": 10.0,
            "total_pnl_cents": -1735.0
          },
          {
            "time": "2026-02-15T04:00:05.215836Z",
            "strategy": "spot_edge",
            "focused_market_count": 3,
            "open_positions": 2,
            "opened": [],
            "closed": [],
            "realized_pnl_cents": -1745.0,
            "unrealized_pnl_cents": 10.0,
            "total_pnl_cents": -1735.0
          },
          {
            "time": "2026-02-15T04:00:20.458208Z",
            "strategy": "spot_edge",
            "focused_market_count": 3,
            "open_positions": 3,
            "opened": [
              {
                "ticker": "KXBTC15M-26FEB142315-15",
                "asset": "BTC",
                "side": "YES",
                "entry": 55.0,
                "score": 22.9,
                "strategy": "spot_edge"
              }
            ],
            "closed": [],
            "realized_pnl_cents": -1745.0,
            "unrealized_pnl_cents": 10.0,
            "total_pnl_cents": -1735.0
          },
          {
            "time": "2026-02-15T04:00:50.320280Z",
            "strategy": "spot_edge",
            "focused_market_count": 3,
            "open_positions": 3,
            "opened": [],
            "closed": [],
            "realized_pnl_cents": -1745.0,
            "unrealized_pnl_cents": 9.0,
            "total_pnl_cents": -1736.0
          },
          {
            "time": "2026-02-15T04:01:05.530459Z",
            "strategy": "spot_edge",
            "focused_market_count": 3,
            "open_positions": 3,
            "opened": [],
            "closed": [],
            "realized_pnl_cents": -1745.0,
            "unrealized_pnl_cents": 8.0,
            "total_pnl_cents": -1737.0
          },
          {
            "time": "2026-02-15T04:01:22.995605Z",
            "strategy": "spot_edge",
            "focused_market_count": 3,
            "open_positions": 3,
            "opened": [],
            "closed": [],
            "realized_pnl_cents": -1745.0,
            "unrealized_pnl_cents": 7.0,
            "total_pnl_cents": -1738.0
          }
        ],
        "open_positions": 3,
        "total_pnl_cents": -1738.0
      }
    }
  },
  "performance": {
    "open_positions": 4,
    "realized_pnl_cents": 0,
    "unrealized_pnl_cents": 0,
    "total_pnl_cents": -6699.97,
    "trades_total": 1134,
    "wins": 244,
    "losses": 862,
    "win_rate": 21.5,
    "by_asset": {
      "BTC": {
        "trades": 308,
        "wins": 92,
        "losses": 206,
        "pnl_cents": -641.0,
        "win_rate": 29.9
      },
      "ETH": {
        "trades": 426,
        "wins": 87,
        "losses": 332,
        "pnl_cents": -1647.0,
        "win_rate": 20.4
      },
      "SOL": {
        "trades": 342,
        "wins": 65,
        "losses": 266,
        "pnl_cents": -1082.0,
        "win_rate": 19.0
      },
      "SPORTS": {
        "trades": 58,
        "wins": 0,
        "losses": 58,
        "pnl_cents": -3329.97,
        "win_rate": 0.0
      }
    },
    "by_strategy": {
      "overreaction_reversion": {
        "trades": 513,
        "wins": 100,
        "losses": 403,
        "win_rate": 19.5,
        "pnl_cents": -1625.0
      },
      "sports_odds_dislocation": {
        "trades": 58,
        "wins": 0,
        "losses": 58,
        "win_rate": 0.0,
        "pnl_cents": -3329.97
      },
      "spot_edge": {
        "trades": 563,
        "wins": 144,
        "losses": 401,
        "win_rate": 25.6,
        "pnl_cents": -1745.0
      }
    }
  },
  "positions": {
    "overreaction_reversion:KXSOL15M-26FEB142245-45": {
      "opened_at": "2026-02-15T03:38:33.411154Z",
      "asset": "SOL",
      "title": "SOL price up in next 15 mins?",
      "strategy": "overreaction_reversion",
      "side": "YES",
      "qty": 1,
      "entry_price": 3.0,
      "mark_price": 0.0,
      "signal": {
        "move_cents": -2.5,
        "vol_cents": 0.449,
        "z": -2.5
      },
      "shadow": false,
      "score": 0.8,
      "unrealized_pnl_cents": -3.0
    },
    "spot_edge:KXETH15M-26FEB142245-45": {
      "opened_at": "2026-02-15T03:36:22.184710Z",
      "asset": "ETH",
      "title": "ETH price up in next 15 mins?",
      "strategy": "spot_edge",
      "side": "NO",
      "qty": 1,
      "entry_price": 94.0,
      "mark_price": 100.0,
      "signal": {
        "mom_bps": -10.504,
        "vol_bps": 6.664,
        "z": -1.576,
        "p_up": 0.1949
      },
      "score": 12.49,
      "unrealized_pnl_cents": 6.0
    },
    "spot_edge:KXSOL15M-26FEB142245-45": {
      "opened_at": "2026-02-15T03:36:52.115714Z",
      "asset": "SOL",
      "title": "SOL price up in next 15 mins?",
      "strategy": "spot_edge",
      "side": "NO",
      "qty": 1,
      "entry_price": 96.0,
      "mark_price": 100.0,
      "signal": {
        "mom_bps": -4.568,
        "vol_bps": 5.161,
        "z": -0.885,
        "p_up": 0.3108
      },
      "shadow": false,
      "score": 26.08,
      "unrealized_pnl_cents": 4.0
    },
    "spot_edge:KXBTC15M-26FEB142315-15": {
      "opened_at": "2026-02-15T04:00:20.447426Z",
      "asset": "BTC",
      "title": "BTC price up in next 15 mins?",
      "strategy": "spot_edge",
      "side": "YES",
      "qty": 1,
      "entry_price": 55.0,
      "mark_price": 52.0,
      "signal": {
        "mom_bps": -4.176,
        "vol_bps": 2.463,
        "z": -1.044,
        "p_up": 0.281
      },
      "shadow": false,
      "score": 22.9,
      "unrealized_pnl_cents": -3.0
    }
  },
  "recent_trades": [
    {
      "time": "2026-02-15T03:39:18.465953Z",
      "ticker": "KXNCAAMBGAME-26FEB15EKYUNA-UNA",
      "asset": "SPORTS",
      "strategy": "sports_odds_dislocation",
      "side": "YES",
      "qty": 1.0,
      "entry": 63.55,
      "exit": 0.0,
      "pnl_cents": -63.55,
      "reason": "stop_loss"
    },
    {
      "time": "2026-02-15T03:39:18.546095Z",
      "ticker": "KXNCAAMBGAME-26FEB15HALLBUT-BUT",
      "asset": "SPORTS",
      "strategy": "sports_odds_dislocation",
      "side": "YES",
      "qty": 1.0,
      "entry": 55.31,
      "exit": 0.0,
      "pnl_cents": -55.31,
      "reason": "stop_loss"
    },
    {
      "time": "2026-02-15T03:39:33.412948Z",
      "ticker": "KXNCAAMBGAME-26FEB15EKYUNA-UNA",
      "asset": "SPORTS",
      "strategy": "sports_odds_dislocation",
      "side": "YES",
      "qty": 1.0,
      "entry": 63.55,
      "exit": 0.0,
      "pnl_cents": -63.55,
      "reason": "stop_loss"
    },
    {
      "time": "2026-02-15T03:39:33.493806Z",
      "ticker": "KXNCAAMBGAME-26FEB15HALLBUT-BUT",
      "asset": "SPORTS",
      "strategy": "sports_odds_dislocation",
      "side": "YES",
      "qty": 1.0,
      "entry": 55.31,
      "exit": 0.0,
      "pnl_cents": -55.31,
      "reason": "stop_loss"
    },
    {
      "time": "2026-02-15T03:39:47.855812Z",
      "ticker": "KXNCAAMBGAME-26FEB15EKYUNA-UNA",
      "asset": "SPORTS",
      "strategy": "sports_odds_dislocation",
      "side": "YES",
      "qty": 1.0,
      "entry": 63.55,
      "exit": 0.0,
      "pnl_cents": -63.55,
      "reason": "stop_loss"
    },
    {
      "time": "2026-02-15T03:39:47.912593Z",
      "ticker": "KXNCAAMBGAME-26FEB15HALLBUT-BUT",
      "asset": "SPORTS",
      "strategy": "sports_odds_dislocation",
      "side": "YES",
      "qty": 1.0,
      "entry": 55.31,
      "exit": 0.0,
      "pnl_cents": -55.31,
      "reason": "stop_loss"
    },
    {
      "time": "2026-02-15T03:40:15.331826Z",
      "ticker": "KXNCAAMBGAME-26FEB15EKYUNA-UNA",
      "asset": "SPORTS",
      "strategy": "sports_odds_dislocation",
      "side": "YES",
      "qty": 1.0,
      "entry": 63.55,
      "exit": 0.0,
      "pnl_cents": -63.55,
      "reason": "stop_loss"
    },
    {
      "time": "2026-02-15T03:40:15.404257Z",
      "ticker": "KXNCAAMBGAME-26FEB15HALLBUT-BUT",
      "asset": "SPORTS",
      "strategy": "sports_odds_dislocation",
      "side": "YES",
      "qty": 1.0,
      "entry": 55.31,
      "exit": 0.0,
      "pnl_cents": -55.31,
      "reason": "stop_loss"
    },
    {
      "time": "2026-02-15T03:40:30.399350Z",
      "ticker": "KXNCAAMBGAME-26FEB15USFFAU-FAU",
      "asset": "SPORTS",
      "strategy": "sports_odds_dislocation",
      "side": "YES",
      "qty": 1.0,
      "entry": 64.91,
      "exit": 0.0,
      "pnl_cents": -64.91,
      "reason": "stop_loss"
    },
    {
      "time": "2026-02-15T03:40:30.485230Z",
      "ticker": "KXNCAAMBGAME-26FEB15EKYUNA-UNA",
      "asset": "SPORTS",
      "strategy": "sports_odds_dislocation",
      "side": "YES",
      "qty": 1.0,
      "entry": 63.55,
      "exit": 0.0,
      "pnl_cents": -63.55,
      "reason": "stop_loss"
    },
    {
      "time": "2026-02-15T03:40:30.555607Z",
      "ticker": "KXNCAAMBGAME-26FEB15HALLBUT-BUT",
      "asset": "SPORTS",
      "strategy": "sports_odds_dislocation",
      "side": "YES",
      "qty": 1.0,
      "entry": 55.31,
      "exit": 0.0,
      "pnl_cents": -55.31,
      "reason": "stop_loss"
    },
    {
      "time": "2026-02-15T03:40:45.904702Z",
      "ticker": "KXNCAAMBGAME-26FEB15USFFAU-FAU",
      "asset": "SPORTS",
      "strategy": "sports_odds_dislocation",
      "side": "YES",
      "qty": 1.0,
      "entry": 64.91,
      "exit": 0.0,
      "pnl_cents": -64.91,
      "reason": "stop_loss"
    },
    {
      "time": "2026-02-15T03:40:46.002284Z",
      "ticker": "KXNCAAMBGAME-26FEB15EKYUNA-UNA",
      "asset": "SPORTS",
      "strategy": "sports_odds_dislocation",
      "side": "YES",
      "qty": 1.0,
      "entry": 63.55,
      "exit": 0.0,
      "pnl_cents": -63.55,
      "reason": "stop_loss"
    },
    {
      "time": "2026-02-15T03:40:46.115275Z",
      "ticker": "KXNCAAMBGAME-26FEB15HALLBUT-BUT",
      "asset": "SPORTS",
      "strategy": "sports_odds_dislocation",
      "side": "YES",
      "qty": 1.0,
      "entry": 55.31,
      "exit": 0.0,
      "pnl_cents": -55.31,
      "reason": "stop_loss"
    },
    {
      "time": "2026-02-15T03:41:00.963524Z",
      "ticker": "KXNCAAMBGAME-26FEB15USFFAU-FAU",
      "asset": "SPORTS",
      "strategy": "sports_odds_dislocation",
      "side": "YES",
      "qty": 1.0,
      "entry": 64.91,
      "exit": 0.0,
      "pnl_cents": -64.91,
      "reason": "stop_loss"
    },
    {
      "time": "2026-02-15T03:41:01.044147Z",
      "ticker": "KXNCAAMBGAME-26FEB15EKYUNA-UNA",
      "asset": "SPORTS",
      "strategy": "sports_odds_dislocation",
      "side": "YES",
      "qty": 1.0,
      "entry": 63.55,
      "exit": 0.0,
      "pnl_cents": -63.55,
      "reason": "stop_loss"
    },
    {
      "time": "2026-02-15T03:41:01.131166Z",
      "ticker": "KXNCAAMBGAME-26FEB15HALLBUT-BUT",
      "asset": "SPORTS",
      "strategy": "sports_odds_dislocation",
      "side": "YES",
      "qty": 1.0,
      "entry": 55.31,
      "exit": 0.0,
      "pnl_cents": -55.31,
      "reason": "stop_loss"
    },
    {
      "time": "2026-02-15T03:41:15.799421Z",
      "ticker": "KXNCAAMBGAME-26FEB15USFFAU-FAU",
      "asset": "SPORTS",
      "strategy": "sports_odds_dislocation",
      "side": "YES",
      "qty": 1.0,
      "entry": 64.91,
      "exit": 0.0,
      "pnl_cents": -64.91,
      "reason": "stop_loss"
    },
    {
      "time": "2026-02-15T03:41:15.863565Z",
      "ticker": "KXNCAAMBGAME-26FEB15EKYUNA-UNA",
      "asset": "SPORTS",
      "strategy": "sports_odds_dislocation",
      "side": "YES",
      "qty": 1.0,
      "entry": 63.55,
      "exit": 0.0,
      "pnl_cents": -63.55,
      "reason": "stop_loss"
    },
    {
      "time": "2026-02-15T03:41:15.938336Z",
      "ticker": "KXNCAAMBGAME-26FEB15HALLBUT-BUT",
      "asset": "SPORTS",
      "strategy": "sports_odds_dislocation",
      "side": "YES",
      "qty": 1.0,
      "entry": 55.31,
      "exit": 0.0,
      "pnl_cents": -55.31,
      "reason": "stop_loss"
    },
    {
      "time": "2026-02-15T03:41:30.629910Z",
      "ticker": "KXNCAAMBGAME-26FEB15USFFAU-FAU",
      "asset": "SPORTS",
      "strategy": "sports_odds_dislocation",
      "side": "YES",
      "qty": 1.0,
      "entry": 64.91,
      "exit": 0.0,
      "pnl_cents": -64.91,
      "reason": "stop_loss"
    },
    {
      "time": "2026-02-15T03:41:30.691765Z",
      "ticker": "KXNCAAMBGAME-26FEB15EKYUNA-UNA",
      "asset": "SPORTS",
      "strategy": "sports_odds_dislocation",
      "side": "YES",
      "qty": 1.0,
      "entry": 63.55,
      "exit": 0.0,
      "pnl_cents": -63.55,
      "reason": "stop_loss"
    },
    {
      "time": "2026-02-15T03:41:30.744820Z",
      "ticker": "KXNCAAMBGAME-26FEB15HALLBUT-BUT",
      "asset": "SPORTS",
      "strategy": "sports_odds_dislocation",
      "side": "YES",
      "qty": 1.0,
      "entry": 55.31,
      "exit": 0.0,
      "pnl_cents": -55.31,
      "reason": "stop_loss"
    },
    {
      "time": "2026-02-15T03:41:45.652093Z",
      "ticker": "KXNCAAMBGAME-26FEB15USFFAU-FAU",
      "asset": "SPORTS",
      "strategy": "sports_odds_dislocation",
      "side": "YES",
      "qty": 1.0,
      "entry": 64.91,
      "exit": 0.0,
      "pnl_cents": -64.91,
      "reason": "stop_loss"
    },
    {
      "time": "2026-02-15T03:41:45.750822Z",
      "ticker": "KXNCAAMBGAME-26FEB15EKYUNA-UNA",
      "asset": "SPORTS",
      "strategy": "sports_odds_dislocation",
      "side": "YES",
      "qty": 1.0,
      "entry": 63.55,
      "exit": 0.0,
      "pnl_cents": -63.55,
      "reason": "stop_loss"
    },
    {
      "time": "2026-02-15T03:41:45.843136Z",
      "ticker": "KXNCAAMBGAME-26FEB15HALLBUT-BUT",
      "asset": "SPORTS",
      "strategy": "sports_odds_dislocation",
      "side": "YES",
      "qty": 1.0,
      "entry": 55.31,
      "exit": 0.0,
      "pnl_cents": -55.31,
      "reason": "stop_loss"
    },
    {
      "time": "2026-02-15T03:42:00.770121Z",
      "ticker": "KXNCAAMBGAME-26FEB15USFFAU-FAU",
      "asset": "SPORTS",
      "strategy": "sports_odds_dislocation",
      "side": "YES",
      "qty": 1.0,
      "entry": 64.91,
      "exit": 0.0,
      "pnl_cents": -64.91,
      "reason": "stop_loss"
    },
    {
      "time": "2026-02-15T03:42:00.869777Z",
      "ticker": "KXNCAAMBGAME-26FEB15EKYUNA-UNA",
      "asset": "SPORTS",
      "strategy": "sports_odds_dislocation",
      "side": "YES",
      "qty": 1.0,
      "entry": 63.55,
      "exit": 0.0,
      "pnl_cents": -63.55,
      "reason": "stop_loss"
    },
    {
      "time": "2026-02-15T03:42:00.988883Z",
      "ticker": "KXNCAAMBGAME-26FEB15HALLBUT-BUT",
      "asset": "SPORTS",
      "strategy": "sports_odds_dislocation",
      "side": "YES",
      "qty": 1.0,
      "entry": 55.31,
      "exit": 0.0,
      "pnl_cents": -55.31,
      "reason": "stop_loss"
    },
    {
      "time": "2026-02-15T03:42:16.162024Z",
      "ticker": "KXNCAAMBGAME-26FEB15USFFAU-FAU",
      "asset": "SPORTS",
      "strategy": "sports_odds_dislocation",
      "side": "YES",
      "qty": 1.0,
      "entry": 64.91,
      "exit": 0.0,
      "pnl_cents": -64.91,
      "reason": "stop_loss"
    },
    {
      "time": "2026-02-15T03:42:16.252849Z",
      "ticker": "KXNCAAMBGAME-26FEB15EKYUNA-UNA",
      "asset": "SPORTS",
      "strategy": "sports_odds_dislocation",
      "side": "YES",
      "qty": 1.0,
      "entry": 63.55,
      "exit": 0.0,
      "pnl_cents": -63.55,
      "reason": "stop_loss"
    },
    {
      "time": "2026-02-15T03:42:16.338304Z",
      "ticker": "KXNCAAMBGAME-26FEB15HALLBUT-BUT",
      "asset": "SPORTS",
      "strategy": "sports_odds_dislocation",
      "side": "YES",
      "qty": 1.0,
      "entry": 55.31,
      "exit": 0.0,
      "pnl_cents": -55.31,
      "reason": "stop_loss"
    },
    {
      "time": "2026-02-15T03:42:31.082725Z",
      "ticker": "KXNCAAMBGAME-26FEB15USFFAU-FAU",
      "asset": "SPORTS",
      "strategy": "sports_odds_dislocation",
      "side": "YES",
      "qty": 1.0,
      "entry": 64.91,
      "exit": 0.0,
      "pnl_cents": -64.91,
      "reason": "stop_loss"
    },
    {
      "time": "2026-02-15T03:42:31.160425Z",
      "ticker": "KXNCAAMBGAME-26FEB15EKYUNA-UNA",
      "asset": "SPORTS",
      "strategy": "sports_odds_dislocation",
      "side": "YES",
      "qty": 1.0,
      "entry": 63.55,
      "exit": 0.0,
      "pnl_cents": -63.55,
      "reason": "stop_loss"
    },
    {
      "time": "2026-02-15T03:42:31.246770Z",
      "ticker": "KXNCAAMBGAME-26FEB15HALLBUT-BUT",
      "asset": "SPORTS",
      "strategy": "sports_odds_dislocation",
      "side": "YES",
      "qty": 1.0,
      "entry": 55.31,
      "exit": 0.0,
      "pnl_cents": -55.31,
      "reason": "stop_loss"
    },
    {
      "time": "2026-02-15T03:42:45.665299Z",
      "ticker": "KXETH15M-26FEB142245-45",
      "asset": "ETH",
      "strategy": "overreaction_reversion",
      "side": "YES",
      "qty": 1.0,
      "entry": 4.0,
      "exit": 0.0,
      "pnl_cents": -4.0,
      "reason": "stop_loss"
    },
    {
      "time": "2026-02-15T03:43:44.853678Z",
      "ticker": "KXBTC15M-26FEB142245-45",
      "asset": "BTC",
      "strategy": "overreaction_reversion",
      "side": "YES",
      "qty": 1.0,
      "entry": 5.0,
      "exit": 0.0,
      "pnl_cents": -5.0,
      "reason": "stop_loss"
    },
    {
      "time": "2026-02-15T03:43:47.083815Z",
      "ticker": "KXBTC15M-26FEB142245-45",
      "asset": "BTC",
      "strategy": "spot_edge",
      "side": "NO",
      "qty": 1.0,
      "entry": 89.0,
      "exit": 99.0,
      "pnl_cents": 10.0,
      "reason": "take_profit"
    },
    {
      "time": "2026-02-15T03:45:31.879812Z",
      "ticker": "KXBTC15M-26FEB142300-00",
      "asset": "BTC",
      "strategy": "spot_edge",
      "side": "YES",
      "qty": 1.0,
      "entry": 47.0,
      "exit": 56.0,
      "pnl_cents": 9.0,
      "reason": "take_profit"
    },
    {
      "time": "2026-02-15T03:45:47.360437Z",
      "ticker": "KXBTC15M-26FEB142300-00",
      "asset": "BTC",
      "strategy": "spot_edge",
      "side": "YES",
      "qty": 1.0,
      "entry": 58.0,
      "exit": 75.0,
      "pnl_cents": 17.0,
      "reason": "take_profit"
    }
  ],
  "guardrails": {
    "trade_enabled": false,
    "live_trading": "disabled",
    "note": "paper only until explicit approval"
  },
  "self_eval": {
    "time": "2026-02-14T15:25:34.948773Z",
    "decision": "no_change",
    "reason": "insufficient_data",
    "trades_analyzed": 4,
    "win_rate_pct": 50.0,
    "expectancy_cents": 0.125,
    "before": {
      "buy_yes_below_cents": 45,
      "sell_yes_above_cents": 55,
      "momentum_min_cents": 0.8,
      "take_profit_cents": 8,
      "stop_loss_cents": 6,
      "max_hold_minutes": 45
    },
    "after": {
      "buy_yes_below_cents": 45,
      "sell_yes_above_cents": 55,
      "momentum_min_cents": 0.8,
      "take_profit_cents": 8,
      "stop_loss_cents": 6,
      "max_hold_minutes": 45
    },
    "changed": false
  },
  "sports_alignment": {
    "generated_at": "2026-02-15T04:00:44.221743Z",
    "aligned_count": 29,
    "top_dislocations": [
      {
        "event_title": "Iona at Niagara",
        "market_ticker": "KXNCAAMBGAME-26FEB15IONANIAG-NIAG",
        "market_title": "Iona at Niagara Winner?",
        "team": "Iona Gaels",
        "kalshi_yes_ask": 30,
        "sportsbook_fair_yes": 67.42,
        "edge_cents": 37.42,
        "competition": "College Basketball (M)"
      },
      {
        "event_title": "Oakland at Robert Morris",
        "market_ticker": "KXNCAAMBGAME-26FEB15OAKRMU-OAK",
        "market_title": "Oakland at Robert Morris Winner?",
        "team": "Oakland Golden Grizzlies",
        "kalshi_yes_ask": 46,
        "sportsbook_fair_yes": 46.47,
        "edge_cents": 0.47,
        "competition": "College Basketball (M)"
      },
      {
        "event_title": "Davidson at Dayton",
        "market_ticker": "KXNCAAMBGAME-26FEB15DAVDAY-DAV",
        "market_title": "Davidson at Dayton Winner?",
        "team": "Davidson Wildcats",
        "kalshi_yes_ask": 37,
        "sportsbook_fair_yes": 37.1,
        "edge_cents": 0.1,
        "competition": "College Basketball (M)"
      }
    ]
  }
}